<?xml version="1.0" encoding="UTF-8"?>
<tva:TVAMain xmlns:tva="urn:tva:metadata:2011" xmlns:mpeg7="urn:tva:mpeg7:2008" xml:lang="en">
  <tva:MetadataOriginationInformationTable>
    <tva:MetadataOriginationInformation originID="-1102226513">
      <tva:Publisher>YouTube</tva:Publisher>
      <tva:RightsOwner>AREternalLove, http://gdata.youtube.com/feeds/api/users/AREternalLove</tva:RightsOwner>
    </tva:MetadataOriginationInformation>
  </tva:MetadataOriginationInformationTable>
  <tva:ProgramDescription>
    <tva:ProgramInformationTable>
      <tva:ProgramInformation fragmentId="72" fragmentVersion="0" programId="crid://youtube.com/i1_ZXeXcjT0">
        <tva:BasicDescription>
          <tva:Title type="main" xml:lang="eng">Iss Pyaar Ko Kya Naam Doon - 4th September, 2012, Full Episode - 334</tva:Title>
          <tva:Synopsis length="long" xml:lang="eng">Episode - 334, Arnav hesitates to enter Anjali's room but Khushi urges him to comfort her. Shyam visits Anjali at the hospital and pretends to be devastated by the loss of their child. Arnav beats him and throws him out but Dadi defends Shyam. Shyam plans to use Anjali's miscarriage as a way to return to Shantivan. Dadi criticizes Arnav for bringing Anjali home from the hospital before her full recovery. Arnav warns his family not to consider bringing Shyam back to Shantivan. credit star India</tva:Synopsis>
          <tva:Genre href="urn:tva:metadata:cs:ContentCS:2011:3.5">
            <tva:Name xml:lang="en">AMUSEMENT/ENTERTAINMENT</tva:Name>
          </tva:Genre>
          <tva:Genre href="urn:tva:metadata:cs:FormatCS:2011:2.7.3.11">
            <tva:Name xml:lang="en">Non-linear audio-video</tva:Name>
            <tva:Definition xml:lang="en">Services where the interaction is based mostly around choosing alternate audio or video files - VOD and AOD, maybe combined with 2.1.1.15 (multi stream)</tva:Definition>
          </tva:Genre>
          <tva:RelatedMaterial>
            <tva:HowRelated href="urn:tva:metadata:cs:HowRelatedCS:2007:6">
              <tva:Name xml:lang="en">Recommendation</tva:Name>
              <tva:Definition xml:lang="en">The reference points to a resource recommended the provider of the current resource. The service provider considers there to be similarities between the
			currently described resource and the referenced resource. Example: This could provide access to previous or next episodes or to all episodes (the parent series as a whole).
			Suggestion to record a programme which the broadcaster recommends because of what the user is watching.It could also point to a Web site proposing related programmes
			‘recommended’ by the service provider. A recommendation can be used to suggest content or services or services bundles with a similar subject.</tva:Definition>
            </tva:HowRelated>
            <tva:Format href="urn:tva:metadata:cs:FormatCS:2011:2.7.3.11">
              <tva:Name xml:lang="en">Non-linear audio-video</tva:Name>
              <tva:Definition xml:lang="en">Services where the interaction is based mostly around choosing alternate audio or video files - VOD and AOD, maybe combined with 2.1.1.15 (multi stream)</tva:Definition>
            </tva:Format>
            <tva:MediaLocator>
              <mpeg7:MediaUri>crid://youtube.com/SXGUdYG9sXg</mpeg7:MediaUri>
            </tva:MediaLocator>
            <tva:PromotionalText xml:lang="eng">iss pyar ko kya naam doon 4th september 2012 part 1</tva:PromotionalText>
            <tva:PromotionalMedia>
              <mpeg7:TitleImage>
                <mpeg7:MediaUri>http://i.ytimg.com/vi/SXGUdYG9sXg/default.jpg</mpeg7:MediaUri>
                <mpeg7:MediaTimePoint>T00:02:57:500F1000</mpeg7:MediaTimePoint>
              </mpeg7:TitleImage>
            </tva:PromotionalMedia>
            <tva:PromotionalMedia>
              <mpeg7:TitleImage>
                <mpeg7:MediaUri>http://i.ytimg.com/vi/SXGUdYG9sXg/mqdefault.jpg</mpeg7:MediaUri>
              </mpeg7:TitleImage>
            </tva:PromotionalMedia>
            <tva:PromotionalMedia>
              <mpeg7:TitleImage>
                <mpeg7:MediaUri>http://i.ytimg.com/vi/SXGUdYG9sXg/hqdefault.jpg</mpeg7:MediaUri>
              </mpeg7:TitleImage>
            </tva:PromotionalMedia>
            <tva:PromotionalMedia>
              <mpeg7:TitleImage>
                <mpeg7:MediaUri>http://i.ytimg.com/vi/SXGUdYG9sXg/1.jpg</mpeg7:MediaUri>
                <mpeg7:MediaTimePoint>T00:01:28:750F1000</mpeg7:MediaTimePoint>
              </mpeg7:TitleImage>
            </tva:PromotionalMedia>
            <tva:PromotionalMedia>
              <mpeg7:TitleImage>
                <mpeg7:MediaUri>http://i.ytimg.com/vi/SXGUdYG9sXg/2.jpg</mpeg7:MediaUri>
                <mpeg7:MediaTimePoint>T00:02:57:500F1000</mpeg7:MediaTimePoint>
              </mpeg7:TitleImage>
            </tva:PromotionalMedia>
            <tva:PromotionalMedia>
              <mpeg7:TitleImage>
                <mpeg7:MediaUri>http://i.ytimg.com/vi/SXGUdYG9sXg/3.jpg</mpeg7:MediaUri>
                <mpeg7:MediaTimePoint>T00:04:26:250F1000</mpeg7:MediaTimePoint>
              </mpeg7:TitleImage>
            </tva:PromotionalMedia>
          </tva:RelatedMaterial>
          <tva:RelatedMaterial>
            <tva:HowRelated href="urn:tva:metadata:cs:HowRelatedCS:2007:6">
              <tva:Name xml:lang="en">Recommendation</tva:Name>
              <tva:Definition xml:lang="en">The reference points to a resource recommended the provider of the current resource. The service provider considers there to be similarities between the
			currently described resource and the referenced resource. Example: This could provide access to previous or next episodes or to all episodes (the parent series as a whole).
			Suggestion to record a programme which the broadcaster recommends because of what the user is watching.It could also point to a Web site proposing related programmes
			‘recommended’ by the service provider. A recommendation can be used to suggest content or services or services bundles with a similar subject.</tva:Definition>
            </tva:HowRelated>
            <tva:Format href="urn:tva:metadata:cs:FormatCS:2011:2.7.3.11">
              <tva:Name xml:lang="en">Non-linear audio-video</tva:Name>
              <tva:Definition xml:lang="en">Services where the interaction is based mostly around choosing alternate audio or video files - VOD and AOD, maybe combined with 2.1.1.15 (multi stream)</tva:Definition>
            </tva:Format>
            <tva:MediaLocator>
              <mpeg7:MediaUri>crid://youtube.com/IwVzjM-ZXD0</mpeg7:MediaUri>
            </tva:MediaLocator>
            <tva:PromotionalText xml:lang="eng">Iss Pyaar Ko Kya Naam Doon : 4th september 2012 part 1 HD watch online</tva:PromotionalText>
            <tva:PromotionalMedia>
              <mpeg7:TitleImage>
                <mpeg7:MediaUri>http://i.ytimg.com/vi/IwVzjM-ZXD0/default.jpg</mpeg7:MediaUri>
                <mpeg7:MediaTimePoint>T00:01:13</mpeg7:MediaTimePoint>
              </mpeg7:TitleImage>
            </tva:PromotionalMedia>
            <tva:PromotionalMedia>
              <mpeg7:TitleImage>
                <mpeg7:MediaUri>http://i.ytimg.com/vi/IwVzjM-ZXD0/mqdefault.jpg</mpeg7:MediaUri>
              </mpeg7:TitleImage>
            </tva:PromotionalMedia>
            <tva:PromotionalMedia>
              <mpeg7:TitleImage>
                <mpeg7:MediaUri>http://i.ytimg.com/vi/IwVzjM-ZXD0/hqdefault.jpg</mpeg7:MediaUri>
              </mpeg7:TitleImage>
            </tva:PromotionalMedia>
            <tva:PromotionalMedia>
              <mpeg7:TitleImage>
                <mpeg7:MediaUri>http://i.ytimg.com/vi/IwVzjM-ZXD0/1.jpg</mpeg7:MediaUri>
                <mpeg7:MediaTimePoint>T00:00:36:500F1000</mpeg7:MediaTimePoint>
              </mpeg7:TitleImage>
            </tva:PromotionalMedia>
            <tva:PromotionalMedia>
              <mpeg7:TitleImage>
                <mpeg7:MediaUri>http://i.ytimg.com/vi/IwVzjM-ZXD0/2.jpg</mpeg7:MediaUri>
                <mpeg7:MediaTimePoint>T00:01:13</mpeg7:MediaTimePoint>
              </mpeg7:TitleImage>
            </tva:PromotionalMedia>
            <tva:PromotionalMedia>
              <mpeg7:TitleImage>
                <mpeg7:MediaUri>http://i.ytimg.com/vi/IwVzjM-ZXD0/3.jpg</mpeg7:MediaUri>
                <mpeg7:MediaTimePoint>T00:01:49:500F1000</mpeg7:MediaTimePoint>
              </mpeg7:TitleImage>
            </tva:PromotionalMedia>
          </tva:RelatedMaterial>
          <tva:RelatedMaterial>
            <tva:HowRelated href="urn:tva:metadata:cs:HowRelatedCS:2007:6">
              <tva:Name xml:lang="en">Recommendation</tva:Name>
              <tva:Definition xml:lang="en">The reference points to a resource recommended the provider of the current resource. The service provider considers there to be similarities between the
			currently described resource and the referenced resource. Example: This could provide access to previous or next episodes or to all episodes (the parent series as a whole).
			Suggestion to record a programme which the broadcaster recommends because of what the user is watching.It could also point to a Web site proposing related programmes
			‘recommended’ by the service provider. A recommendation can be used to suggest content or services or services bundles with a similar subject.</tva:Definition>
            </tva:HowRelated>
            <tva:Format href="urn:tva:metadata:cs:FormatCS:2011:2.7.3.11">
              <tva:Name xml:lang="en">Non-linear audio-video</tva:Name>
              <tva:Definition xml:lang="en">Services where the interaction is based mostly around choosing alternate audio or video files - VOD and AOD, maybe combined with 2.1.1.15 (multi stream)</tva:Definition>
            </tva:Format>
            <tva:MediaLocator>
              <mpeg7:MediaUri>crid://youtube.com/hcltY6GaDPA</mpeg7:MediaUri>
            </tva:MediaLocator>
            <tva:PromotionalText xml:lang="eng">Iss Pyaar Ko Kya Naam Doon - 4th september 2012 part 1 HD watch online</tva:PromotionalText>
            <tva:PromotionalMedia>
              <mpeg7:TitleImage>
                <mpeg7:MediaUri>http://i.ytimg.com/vi/hcltY6GaDPA/default.jpg</mpeg7:MediaUri>
                <mpeg7:MediaTimePoint>T00:03:42:500F1000</mpeg7:MediaTimePoint>
              </mpeg7:TitleImage>
            </tva:PromotionalMedia>
            <tva:PromotionalMedia>
              <mpeg7:TitleImage>
                <mpeg7:MediaUri>http://i.ytimg.com/vi/hcltY6GaDPA/mqdefault.jpg</mpeg7:MediaUri>
              </mpeg7:TitleImage>
            </tva:PromotionalMedia>
            <tva:PromotionalMedia>
              <mpeg7:TitleImage>
                <mpeg7:MediaUri>http://i.ytimg.com/vi/hcltY6GaDPA/hqdefault.jpg</mpeg7:MediaUri>
              </mpeg7:TitleImage>
            </tva:PromotionalMedia>
            <tva:PromotionalMedia>
              <mpeg7:TitleImage>
                <mpeg7:MediaUri>http://i.ytimg.com/vi/hcltY6GaDPA/1.jpg</mpeg7:MediaUri>
                <mpeg7:MediaTimePoint>T00:01:51:250F1000</mpeg7:MediaTimePoint>
              </mpeg7:TitleImage>
            </tva:PromotionalMedia>
            <tva:PromotionalMedia>
              <mpeg7:TitleImage>
                <mpeg7:MediaUri>http://i.ytimg.com/vi/hcltY6GaDPA/2.jpg</mpeg7:MediaUri>
                <mpeg7:MediaTimePoint>T00:03:42:500F1000</mpeg7:MediaTimePoint>
              </mpeg7:TitleImage>
            </tva:PromotionalMedia>
            <tva:PromotionalMedia>
              <mpeg7:TitleImage>
                <mpeg7:MediaUri>http://i.ytimg.com/vi/hcltY6GaDPA/3.jpg</mpeg7:MediaUri>
                <mpeg7:MediaTimePoint>T00:05:33:750F1000</mpeg7:MediaTimePoint>
              </mpeg7:TitleImage>
            </tva:PromotionalMedia>
          </tva:RelatedMaterial>
          <tva:RelatedMaterial>
            <tva:HowRelated href="urn:tva:metadata:cs:HowRelatedCS:2007:6">
              <tva:Name xml:lang="en">Recommendation</tva:Name>
              <tva:Definition xml:lang="en">The reference points to a resource recommended the provider of the current resource. The service provider considers there to be similarities between the
			currently described resource and the referenced resource. Example: This could provide access to previous or next episodes or to all episodes (the parent series as a whole).
			Suggestion to record a programme which the broadcaster recommends because of what the user is watching.It could also point to a Web site proposing related programmes
			‘recommended’ by the service provider. A recommendation can be used to suggest content or services or services bundles with a similar subject.</tva:Definition>
            </tva:HowRelated>
            <tva:Format href="urn:tva:metadata:cs:FormatCS:2011:2.7.3.11">
              <tva:Name xml:lang="en">Non-linear audio-video</tva:Name>
              <tva:Definition xml:lang="en">Services where the interaction is based mostly around choosing alternate audio or video files - VOD and AOD, maybe combined with 2.1.1.15 (multi stream)</tva:Definition>
            </tva:Format>
            <tva:MediaLocator>
              <mpeg7:MediaUri>crid://youtube.com/9vq0rnZ4ISY</mpeg7:MediaUri>
            </tva:MediaLocator>
            <tva:PromotionalText xml:lang="eng">iss pyar ko kya naam doon 4th september 2012 part 2 watch video</tva:PromotionalText>
            <tva:PromotionalMedia>
              <mpeg7:TitleImage>
                <mpeg7:MediaUri>http://i.ytimg.com/vi/9vq0rnZ4ISY/default.jpg</mpeg7:MediaUri>
                <mpeg7:MediaTimePoint>T00:02:57:500F1000</mpeg7:MediaTimePoint>
              </mpeg7:TitleImage>
            </tva:PromotionalMedia>
            <tva:PromotionalMedia>
              <mpeg7:TitleImage>
                <mpeg7:MediaUri>http://i.ytimg.com/vi/9vq0rnZ4ISY/mqdefault.jpg</mpeg7:MediaUri>
              </mpeg7:TitleImage>
            </tva:PromotionalMedia>
            <tva:PromotionalMedia>
              <mpeg7:TitleImage>
                <mpeg7:MediaUri>http://i.ytimg.com/vi/9vq0rnZ4ISY/hqdefault.jpg</mpeg7:MediaUri>
              </mpeg7:TitleImage>
            </tva:PromotionalMedia>
            <tva:PromotionalMedia>
              <mpeg7:TitleImage>
                <mpeg7:MediaUri>http://i.ytimg.com/vi/9vq0rnZ4ISY/1.jpg</mpeg7:MediaUri>
                <mpeg7:MediaTimePoint>T00:01:28:750F1000</mpeg7:MediaTimePoint>
              </mpeg7:TitleImage>
            </tva:PromotionalMedia>
            <tva:PromotionalMedia>
              <mpeg7:TitleImage>
                <mpeg7:MediaUri>http://i.ytimg.com/vi/9vq0rnZ4ISY/2.jpg</mpeg7:MediaUri>
                <mpeg7:MediaTimePoint>T00:02:57:500F1000</mpeg7:MediaTimePoint>
              </mpeg7:TitleImage>
            </tva:PromotionalMedia>
            <tva:PromotionalMedia>
              <mpeg7:TitleImage>
                <mpeg7:MediaUri>http://i.ytimg.com/vi/9vq0rnZ4ISY/3.jpg</mpeg7:MediaUri>
                <mpeg7:MediaTimePoint>T00:04:26:250F1000</mpeg7:MediaTimePoint>
              </mpeg7:TitleImage>
            </tva:PromotionalMedia>
          </tva:RelatedMaterial>
          <tva:RelatedMaterial>
            <tva:HowRelated href="urn:tva:metadata:cs:HowRelatedCS:2007:6">
              <tva:Name xml:lang="en">Recommendation</tva:Name>
              <tva:Definition xml:lang="en">The reference points to a resource recommended the provider of the current resource. The service provider considers there to be similarities between the
			currently described resource and the referenced resource. Example: This could provide access to previous or next episodes or to all episodes (the parent series as a whole).
			Suggestion to record a programme which the broadcaster recommends because of what the user is watching.It could also point to a Web site proposing related programmes
			‘recommended’ by the service provider. A recommendation can be used to suggest content or services or services bundles with a similar subject.</tva:Definition>
            </tva:HowRelated>
            <tva:Format href="urn:tva:metadata:cs:FormatCS:2011:2.7.3.11">
              <tva:Name xml:lang="en">Non-linear audio-video</tva:Name>
              <tva:Definition xml:lang="en">Services where the interaction is based mostly around choosing alternate audio or video files - VOD and AOD, maybe combined with 2.1.1.15 (multi stream)</tva:Definition>
            </tva:Format>
            <tva:MediaLocator>
              <mpeg7:MediaUri>crid://youtube.com/lpPLtTsS_SA</mpeg7:MediaUri>
            </tva:MediaLocator>
            <tva:PromotionalText xml:lang="eng">iss pyar ko kya naam doon 4th september 2012 part 5</tva:PromotionalText>
            <tva:PromotionalMedia>
              <mpeg7:TitleImage>
                <mpeg7:MediaUri>http://i.ytimg.com/vi/lpPLtTsS_SA/default.jpg</mpeg7:MediaUri>
                <mpeg7:MediaTimePoint>T00:01:36:500F1000</mpeg7:MediaTimePoint>
              </mpeg7:TitleImage>
            </tva:PromotionalMedia>
            <tva:PromotionalMedia>
              <mpeg7:TitleImage>
                <mpeg7:MediaUri>http://i.ytimg.com/vi/lpPLtTsS_SA/mqdefault.jpg</mpeg7:MediaUri>
              </mpeg7:TitleImage>
            </tva:PromotionalMedia>
            <tva:PromotionalMedia>
              <mpeg7:TitleImage>
                <mpeg7:MediaUri>http://i.ytimg.com/vi/lpPLtTsS_SA/hqdefault.jpg</mpeg7:MediaUri>
              </mpeg7:TitleImage>
            </tva:PromotionalMedia>
            <tva:PromotionalMedia>
              <mpeg7:TitleImage>
                <mpeg7:MediaUri>http://i.ytimg.com/vi/lpPLtTsS_SA/1.jpg</mpeg7:MediaUri>
                <mpeg7:MediaTimePoint>T00:00:48:250F1000</mpeg7:MediaTimePoint>
              </mpeg7:TitleImage>
            </tva:PromotionalMedia>
            <tva:PromotionalMedia>
              <mpeg7:TitleImage>
                <mpeg7:MediaUri>http://i.ytimg.com/vi/lpPLtTsS_SA/2.jpg</mpeg7:MediaUri>
                <mpeg7:MediaTimePoint>T00:01:36:500F1000</mpeg7:MediaTimePoint>
              </mpeg7:TitleImage>
            </tva:PromotionalMedia>
            <tva:PromotionalMedia>
              <mpeg7:TitleImage>
                <mpeg7:MediaUri>http://i.ytimg.com/vi/lpPLtTsS_SA/3.jpg</mpeg7:MediaUri>
                <mpeg7:MediaTimePoint>T00:02:24:750F1000</mpeg7:MediaTimePoint>
              </mpeg7:TitleImage>
            </tva:PromotionalMedia>
          </tva:RelatedMaterial>
          <tva:RelatedMaterial>
            <tva:HowRelated href="urn:tva:metadata:cs:HowRelatedCS:2007:6">
              <tva:Name xml:lang="en">Recommendation</tva:Name>
              <tva:Definition xml:lang="en">The reference points to a resource recommended the provider of the current resource. The service provider considers there to be similarities between the
			currently described resource and the referenced resource. Example: This could provide access to previous or next episodes or to all episodes (the parent series as a whole).
			Suggestion to record a programme which the broadcaster recommends because of what the user is watching.It could also point to a Web site proposing related programmes
			‘recommended’ by the service provider. A recommendation can be used to suggest content or services or services bundles with a similar subject.</tva:Definition>
            </tva:HowRelated>
            <tva:Format href="urn:tva:metadata:cs:FormatCS:2011:2.7.3.11">
              <tva:Name xml:lang="en">Non-linear audio-video</tva:Name>
              <tva:Definition xml:lang="en">Services where the interaction is based mostly around choosing alternate audio or video files - VOD and AOD, maybe combined with 2.1.1.15 (multi stream)</tva:Definition>
            </tva:Format>
            <tva:MediaLocator>
              <mpeg7:MediaUri>crid://youtube.com/zaE1rUpOnW0</mpeg7:MediaUri>
            </tva:MediaLocator>
            <tva:PromotionalText xml:lang="eng">iss pyar ko kya naam doon 4th september 2012 part 2</tva:PromotionalText>
            <tva:PromotionalMedia>
              <mpeg7:TitleImage>
                <mpeg7:MediaUri>http://i.ytimg.com/vi/zaE1rUpOnW0/default.jpg</mpeg7:MediaUri>
                <mpeg7:MediaTimePoint>T00:01:33</mpeg7:MediaTimePoint>
              </mpeg7:TitleImage>
            </tva:PromotionalMedia>
            <tva:PromotionalMedia>
              <mpeg7:TitleImage>
                <mpeg7:MediaUri>http://i.ytimg.com/vi/zaE1rUpOnW0/mqdefault.jpg</mpeg7:MediaUri>
              </mpeg7:TitleImage>
            </tva:PromotionalMedia>
            <tva:PromotionalMedia>
              <mpeg7:TitleImage>
                <mpeg7:MediaUri>http://i.ytimg.com/vi/zaE1rUpOnW0/hqdefault.jpg</mpeg7:MediaUri>
              </mpeg7:TitleImage>
            </tva:PromotionalMedia>
            <tva:PromotionalMedia>
              <mpeg7:TitleImage>
                <mpeg7:MediaUri>http://i.ytimg.com/vi/zaE1rUpOnW0/1.jpg</mpeg7:MediaUri>
                <mpeg7:MediaTimePoint>T00:00:46:500F1000</mpeg7:MediaTimePoint>
              </mpeg7:TitleImage>
            </tva:PromotionalMedia>
            <tva:PromotionalMedia>
              <mpeg7:TitleImage>
                <mpeg7:MediaUri>http://i.ytimg.com/vi/zaE1rUpOnW0/2.jpg</mpeg7:MediaUri>
                <mpeg7:MediaTimePoint>T00:01:33</mpeg7:MediaTimePoint>
              </mpeg7:TitleImage>
            </tva:PromotionalMedia>
            <tva:PromotionalMedia>
              <mpeg7:TitleImage>
                <mpeg7:MediaUri>http://i.ytimg.com/vi/zaE1rUpOnW0/3.jpg</mpeg7:MediaUri>
                <mpeg7:MediaTimePoint>T00:02:19:500F1000</mpeg7:MediaTimePoint>
              </mpeg7:TitleImage>
            </tva:PromotionalMedia>
          </tva:RelatedMaterial>
          <tva:RelatedMaterial>
            <tva:HowRelated href="urn:tva:metadata:cs:HowRelatedCS:2007:6">
              <tva:Name xml:lang="en">Recommendation</tva:Name>
              <tva:Definition xml:lang="en">The reference points to a resource recommended the provider of the current resource. The service provider considers there to be similarities between the
			currently described resource and the referenced resource. Example: This could provide access to previous or next episodes or to all episodes (the parent series as a whole).
			Suggestion to record a programme which the broadcaster recommends because of what the user is watching.It could also point to a Web site proposing related programmes
			‘recommended’ by the service provider. A recommendation can be used to suggest content or services or services bundles with a similar subject.</tva:Definition>
            </tva:HowRelated>
            <tva:Format href="urn:tva:metadata:cs:FormatCS:2011:2.7.3.11">
              <tva:Name xml:lang="en">Non-linear audio-video</tva:Name>
              <tva:Definition xml:lang="en">Services where the interaction is based mostly around choosing alternate audio or video files - VOD and AOD, maybe combined with 2.1.1.15 (multi stream)</tva:Definition>
            </tva:Format>
            <tva:MediaLocator>
              <mpeg7:MediaUri>crid://youtube.com/6S_7k2ASy8Y</mpeg7:MediaUri>
            </tva:MediaLocator>
            <tva:PromotionalText xml:lang="eng">Iss Pyaar Ko Kya Naam Doon : 4th september 2012 part 5 HD watch online</tva:PromotionalText>
            <tva:PromotionalMedia>
              <mpeg7:TitleImage>
                <mpeg7:MediaUri>http://i.ytimg.com/vi/6S_7k2ASy8Y/default.jpg</mpeg7:MediaUri>
                <mpeg7:MediaTimePoint>T00:00:54:500F1000</mpeg7:MediaTimePoint>
              </mpeg7:TitleImage>
            </tva:PromotionalMedia>
            <tva:PromotionalMedia>
              <mpeg7:TitleImage>
                <mpeg7:MediaUri>http://i.ytimg.com/vi/6S_7k2ASy8Y/mqdefault.jpg</mpeg7:MediaUri>
              </mpeg7:TitleImage>
            </tva:PromotionalMedia>
            <tva:PromotionalMedia>
              <mpeg7:TitleImage>
                <mpeg7:MediaUri>http://i.ytimg.com/vi/6S_7k2ASy8Y/hqdefault.jpg</mpeg7:MediaUri>
              </mpeg7:TitleImage>
            </tva:PromotionalMedia>
            <tva:PromotionalMedia>
              <mpeg7:TitleImage>
                <mpeg7:MediaUri>http://i.ytimg.com/vi/6S_7k2ASy8Y/1.jpg</mpeg7:MediaUri>
                <mpeg7:MediaTimePoint>T00:00:27:250F1000</mpeg7:MediaTimePoint>
              </mpeg7:TitleImage>
            </tva:PromotionalMedia>
            <tva:PromotionalMedia>
              <mpeg7:TitleImage>
                <mpeg7:MediaUri>http://i.ytimg.com/vi/6S_7k2ASy8Y/2.jpg</mpeg7:MediaUri>
                <mpeg7:MediaTimePoint>T00:00:54:500F1000</mpeg7:MediaTimePoint>
              </mpeg7:TitleImage>
            </tva:PromotionalMedia>
            <tva:PromotionalMedia>
              <mpeg7:TitleImage>
                <mpeg7:MediaUri>http://i.ytimg.com/vi/6S_7k2ASy8Y/3.jpg</mpeg7:MediaUri>
                <mpeg7:MediaTimePoint>T00:01:21:750F1000</mpeg7:MediaTimePoint>
              </mpeg7:TitleImage>
            </tva:PromotionalMedia>
          </tva:RelatedMaterial>
          <tva:RelatedMaterial>
            <tva:HowRelated href="urn:tva:metadata:cs:HowRelatedCS:2007:6">
              <tva:Name xml:lang="en">Recommendation</tva:Name>
              <tva:Definition xml:lang="en">The reference points to a resource recommended the provider of the current resource. The service provider considers there to be similarities between the
			currently described resource and the referenced resource. Example: This could provide access to previous or next episodes or to all episodes (the parent series as a whole).
			Suggestion to record a programme which the broadcaster recommends because of what the user is watching.It could also point to a Web site proposing related programmes
			‘recommended’ by the service provider. A recommendation can be used to suggest content or services or services bundles with a similar subject.</tva:Definition>
            </tva:HowRelated>
            <tva:Format href="urn:tva:metadata:cs:FormatCS:2011:2.7.3.11">
              <tva:Name xml:lang="en">Non-linear audio-video</tva:Name>
              <tva:Definition xml:lang="en">Services where the interaction is based mostly around choosing alternate audio or video files - VOD and AOD, maybe combined with 2.1.1.15 (multi stream)</tva:Definition>
            </tva:Format>
            <tva:MediaLocator>
              <mpeg7:MediaUri>crid://youtube.com/0CNn6RrQUyo</mpeg7:MediaUri>
            </tva:MediaLocator>
            <tva:PromotionalText xml:lang="eng">iss pyar ko kya naam doon 4th september 2012 part 1</tva:PromotionalText>
            <tva:PromotionalMedia>
              <mpeg7:TitleImage>
                <mpeg7:MediaUri>http://i.ytimg.com/vi/0CNn6RrQUyo/default.jpg</mpeg7:MediaUri>
                <mpeg7:MediaTimePoint>T00:01:47:500F1000</mpeg7:MediaTimePoint>
              </mpeg7:TitleImage>
            </tva:PromotionalMedia>
            <tva:PromotionalMedia>
              <mpeg7:TitleImage>
                <mpeg7:MediaUri>http://i.ytimg.com/vi/0CNn6RrQUyo/mqdefault.jpg</mpeg7:MediaUri>
              </mpeg7:TitleImage>
            </tva:PromotionalMedia>
            <tva:PromotionalMedia>
              <mpeg7:TitleImage>
                <mpeg7:MediaUri>http://i.ytimg.com/vi/0CNn6RrQUyo/hqdefault.jpg</mpeg7:MediaUri>
              </mpeg7:TitleImage>
            </tva:PromotionalMedia>
            <tva:PromotionalMedia>
              <mpeg7:TitleImage>
                <mpeg7:MediaUri>http://i.ytimg.com/vi/0CNn6RrQUyo/1.jpg</mpeg7:MediaUri>
                <mpeg7:MediaTimePoint>T00:00:53:750F1000</mpeg7:MediaTimePoint>
              </mpeg7:TitleImage>
            </tva:PromotionalMedia>
            <tva:PromotionalMedia>
              <mpeg7:TitleImage>
                <mpeg7:MediaUri>http://i.ytimg.com/vi/0CNn6RrQUyo/2.jpg</mpeg7:MediaUri>
                <mpeg7:MediaTimePoint>T00:01:47:500F1000</mpeg7:MediaTimePoint>
              </mpeg7:TitleImage>
            </tva:PromotionalMedia>
            <tva:PromotionalMedia>
              <mpeg7:TitleImage>
                <mpeg7:MediaUri>http://i.ytimg.com/vi/0CNn6RrQUyo/3.jpg</mpeg7:MediaUri>
                <mpeg7:MediaTimePoint>T00:02:41:250F1000</mpeg7:MediaTimePoint>
              </mpeg7:TitleImage>
            </tva:PromotionalMedia>
          </tva:RelatedMaterial>
          <tva:RelatedMaterial>
            <tva:HowRelated href="urn:tva:metadata:cs:HowRelatedCS:2007:6">
              <tva:Name xml:lang="en">Recommendation</tva:Name>
              <tva:Definition xml:lang="en">The reference points to a resource recommended the provider of the current resource. The service provider considers there to be similarities between the
			currently described resource and the referenced resource. Example: This could provide access to previous or next episodes or to all episodes (the parent series as a whole).
			Suggestion to record a programme which the broadcaster recommends because of what the user is watching.It could also point to a Web site proposing related programmes
			‘recommended’ by the service provider. A recommendation can be used to suggest content or services or services bundles with a similar subject.</tva:Definition>
            </tva:HowRelated>
            <tva:Format href="urn:tva:metadata:cs:FormatCS:2011:2.7.3.11">
              <tva:Name xml:lang="en">Non-linear audio-video</tva:Name>
              <tva:Definition xml:lang="en">Services where the interaction is based mostly around choosing alternate audio or video files - VOD and AOD, maybe combined with 2.1.1.15 (multi stream)</tva:Definition>
            </tva:Format>
            <tva:MediaLocator>
              <mpeg7:MediaUri>crid://youtube.com/5Mtih3UxScA</mpeg7:MediaUri>
            </tva:MediaLocator>
            <tva:PromotionalText xml:lang="eng">iss pyar ko kya naam doon 4th september 2012 part 1</tva:PromotionalText>
            <tva:PromotionalMedia>
              <mpeg7:TitleImage>
                <mpeg7:MediaUri>http://i.ytimg.com/vi/5Mtih3UxScA/default.jpg</mpeg7:MediaUri>
                <mpeg7:MediaTimePoint>T00:01:53</mpeg7:MediaTimePoint>
              </mpeg7:TitleImage>
            </tva:PromotionalMedia>
            <tva:PromotionalMedia>
              <mpeg7:TitleImage>
                <mpeg7:MediaUri>http://i.ytimg.com/vi/5Mtih3UxScA/mqdefault.jpg</mpeg7:MediaUri>
              </mpeg7:TitleImage>
            </tva:PromotionalMedia>
            <tva:PromotionalMedia>
              <mpeg7:TitleImage>
                <mpeg7:MediaUri>http://i.ytimg.com/vi/5Mtih3UxScA/hqdefault.jpg</mpeg7:MediaUri>
              </mpeg7:TitleImage>
            </tva:PromotionalMedia>
            <tva:PromotionalMedia>
              <mpeg7:TitleImage>
                <mpeg7:MediaUri>http://i.ytimg.com/vi/5Mtih3UxScA/1.jpg</mpeg7:MediaUri>
                <mpeg7:MediaTimePoint>T00:00:56:500F1000</mpeg7:MediaTimePoint>
              </mpeg7:TitleImage>
            </tva:PromotionalMedia>
            <tva:PromotionalMedia>
              <mpeg7:TitleImage>
                <mpeg7:MediaUri>http://i.ytimg.com/vi/5Mtih3UxScA/2.jpg</mpeg7:MediaUri>
                <mpeg7:MediaTimePoint>T00:01:53</mpeg7:MediaTimePoint>
              </mpeg7:TitleImage>
            </tva:PromotionalMedia>
            <tva:PromotionalMedia>
              <mpeg7:TitleImage>
                <mpeg7:MediaUri>http://i.ytimg.com/vi/5Mtih3UxScA/3.jpg</mpeg7:MediaUri>
                <mpeg7:MediaTimePoint>T00:02:49:500F1000</mpeg7:MediaTimePoint>
              </mpeg7:TitleImage>
            </tva:PromotionalMedia>
          </tva:RelatedMaterial>
          <tva:RelatedMaterial>
            <tva:HowRelated href="urn:tva:metadata:cs:HowRelatedCS:2007:6">
              <tva:Name xml:lang="en">Recommendation</tva:Name>
              <tva:Definition xml:lang="en">The reference points to a resource recommended the provider of the current resource. The service provider considers there to be similarities between the
			currently described resource and the referenced resource. Example: This could provide access to previous or next episodes or to all episodes (the parent series as a whole).
			Suggestion to record a programme which the broadcaster recommends because of what the user is watching.It could also point to a Web site proposing related programmes
			‘recommended’ by the service provider. A recommendation can be used to suggest content or services or services bundles with a similar subject.</tva:Definition>
            </tva:HowRelated>
            <tva:Format href="urn:tva:metadata:cs:FormatCS:2011:2.7.3.11">
              <tva:Name xml:lang="en">Non-linear audio-video</tva:Name>
              <tva:Definition xml:lang="en">Services where the interaction is based mostly around choosing alternate audio or video files - VOD and AOD, maybe combined with 2.1.1.15 (multi stream)</tva:Definition>
            </tva:Format>
            <tva:MediaLocator>
              <mpeg7:MediaUri>crid://youtube.com/Jn5IQbMNENU</mpeg7:MediaUri>
            </tva:MediaLocator>
            <tva:PromotionalText xml:lang="eng">Iss Pyaar Ko Kya Naam Doon - 4th september 2012 part 1 HD watch online</tva:PromotionalText>
            <tva:PromotionalMedia>
              <mpeg7:TitleImage>
                <mpeg7:MediaUri>http://i.ytimg.com/vi/Jn5IQbMNENU/default.jpg</mpeg7:MediaUri>
                <mpeg7:MediaTimePoint>T00:03:42</mpeg7:MediaTimePoint>
              </mpeg7:TitleImage>
            </tva:PromotionalMedia>
            <tva:PromotionalMedia>
              <mpeg7:TitleImage>
                <mpeg7:MediaUri>http://i.ytimg.com/vi/Jn5IQbMNENU/mqdefault.jpg</mpeg7:MediaUri>
              </mpeg7:TitleImage>
            </tva:PromotionalMedia>
            <tva:PromotionalMedia>
              <mpeg7:TitleImage>
                <mpeg7:MediaUri>http://i.ytimg.com/vi/Jn5IQbMNENU/hqdefault.jpg</mpeg7:MediaUri>
              </mpeg7:TitleImage>
            </tva:PromotionalMedia>
            <tva:PromotionalMedia>
              <mpeg7:TitleImage>
                <mpeg7:MediaUri>http://i.ytimg.com/vi/Jn5IQbMNENU/1.jpg</mpeg7:MediaUri>
                <mpeg7:MediaTimePoint>T00:01:51</mpeg7:MediaTimePoint>
              </mpeg7:TitleImage>
            </tva:PromotionalMedia>
            <tva:PromotionalMedia>
              <mpeg7:TitleImage>
                <mpeg7:MediaUri>http://i.ytimg.com/vi/Jn5IQbMNENU/2.jpg</mpeg7:MediaUri>
                <mpeg7:MediaTimePoint>T00:03:42</mpeg7:MediaTimePoint>
              </mpeg7:TitleImage>
            </tva:PromotionalMedia>
            <tva:PromotionalMedia>
              <mpeg7:TitleImage>
                <mpeg7:MediaUri>http://i.ytimg.com/vi/Jn5IQbMNENU/3.jpg</mpeg7:MediaUri>
                <mpeg7:MediaTimePoint>T00:05:33</mpeg7:MediaTimePoint>
              </mpeg7:TitleImage>
            </tva:PromotionalMedia>
          </tva:RelatedMaterial>
          <tva:RelatedMaterial>
            <tva:HowRelated href="urn:tva:metadata:cs:HowRelatedCS:2007:6">
              <tva:Name xml:lang="en">Recommendation</tva:Name>
              <tva:Definition xml:lang="en">The reference points to a resource recommended the provider of the current resource. The service provider considers there to be similarities between the
			currently described resource and the referenced resource. Example: This could provide access to previous or next episodes or to all episodes (the parent series as a whole).
			Suggestion to record a programme which the broadcaster recommends because of what the user is watching.It could also point to a Web site proposing related programmes
			‘recommended’ by the service provider. A recommendation can be used to suggest content or services or services bundles with a similar subject.</tva:Definition>
            </tva:HowRelated>
            <tva:Format href="urn:tva:metadata:cs:FormatCS:2011:2.7.3.11">
              <tva:Name xml:lang="en">Non-linear audio-video</tva:Name>
              <tva:Definition xml:lang="en">Services where the interaction is based mostly around choosing alternate audio or video files - VOD and AOD, maybe combined with 2.1.1.15 (multi stream)</tva:Definition>
            </tva:Format>
            <tva:MediaLocator>
              <mpeg7:MediaUri>crid://youtube.com/Hm1gOwUDHOI</mpeg7:MediaUri>
            </tva:MediaLocator>
            <tva:PromotionalText xml:lang="eng">Iss Pyaar Ko Kya Naam Doon : 4th september 2012 part 4 HD watch online</tva:PromotionalText>
            <tva:PromotionalMedia>
              <mpeg7:TitleImage>
                <mpeg7:MediaUri>http://i.ytimg.com/vi/Hm1gOwUDHOI/default.jpg</mpeg7:MediaUri>
                <mpeg7:MediaTimePoint>T00:01:54</mpeg7:MediaTimePoint>
              </mpeg7:TitleImage>
            </tva:PromotionalMedia>
            <tva:PromotionalMedia>
              <mpeg7:TitleImage>
                <mpeg7:MediaUri>http://i.ytimg.com/vi/Hm1gOwUDHOI/mqdefault.jpg</mpeg7:MediaUri>
              </mpeg7:TitleImage>
            </tva:PromotionalMedia>
            <tva:PromotionalMedia>
              <mpeg7:TitleImage>
                <mpeg7:MediaUri>http://i.ytimg.com/vi/Hm1gOwUDHOI/hqdefault.jpg</mpeg7:MediaUri>
              </mpeg7:TitleImage>
            </tva:PromotionalMedia>
            <tva:PromotionalMedia>
              <mpeg7:TitleImage>
                <mpeg7:MediaUri>http://i.ytimg.com/vi/Hm1gOwUDHOI/1.jpg</mpeg7:MediaUri>
                <mpeg7:MediaTimePoint>T00:00:57</mpeg7:MediaTimePoint>
              </mpeg7:TitleImage>
            </tva:PromotionalMedia>
            <tva:PromotionalMedia>
              <mpeg7:TitleImage>
                <mpeg7:MediaUri>http://i.ytimg.com/vi/Hm1gOwUDHOI/2.jpg</mpeg7:MediaUri>
                <mpeg7:MediaTimePoint>T00:01:54</mpeg7:MediaTimePoint>
              </mpeg7:TitleImage>
            </tva:PromotionalMedia>
            <tva:PromotionalMedia>
              <mpeg7:TitleImage>
                <mpeg7:MediaUri>http://i.ytimg.com/vi/Hm1gOwUDHOI/3.jpg</mpeg7:MediaUri>
                <mpeg7:MediaTimePoint>T00:02:51</mpeg7:MediaTimePoint>
              </mpeg7:TitleImage>
            </tva:PromotionalMedia>
          </tva:RelatedMaterial>
          <tva:RelatedMaterial>
            <tva:HowRelated href="urn:tva:metadata:cs:HowRelatedCS:2007:6">
              <tva:Name xml:lang="en">Recommendation</tva:Name>
              <tva:Definition xml:lang="en">The reference points to a resource recommended the provider of the current resource. The service provider considers there to be similarities between the
			currently described resource and the referenced resource. Example: This could provide access to previous or next episodes or to all episodes (the parent series as a whole).
			Suggestion to record a programme which the broadcaster recommends because of what the user is watching.It could also point to a Web site proposing related programmes
			‘recommended’ by the service provider. A recommendation can be used to suggest content or services or services bundles with a similar subject.</tva:Definition>
            </tva:HowRelated>
            <tva:Format href="urn:tva:metadata:cs:FormatCS:2011:2.7.3.11">
              <tva:Name xml:lang="en">Non-linear audio-video</tva:Name>
              <tva:Definition xml:lang="en">Services where the interaction is based mostly around choosing alternate audio or video files - VOD and AOD, maybe combined with 2.1.1.15 (multi stream)</tva:Definition>
            </tva:Format>
            <tva:MediaLocator>
              <mpeg7:MediaUri>crid://youtube.com/wMc_5-RSWeg</mpeg7:MediaUri>
            </tva:MediaLocator>
            <tva:PromotionalText xml:lang="eng">Iss Pyaar Ko Kya Naam Doon - 4th september 2012 part 1 HD watch online</tva:PromotionalText>
            <tva:PromotionalMedia>
              <mpeg7:TitleImage>
                <mpeg7:MediaUri>http://i.ytimg.com/vi/wMc_5-RSWeg/default.jpg</mpeg7:MediaUri>
                <mpeg7:MediaTimePoint>T00:01:51</mpeg7:MediaTimePoint>
              </mpeg7:TitleImage>
            </tva:PromotionalMedia>
            <tva:PromotionalMedia>
              <mpeg7:TitleImage>
                <mpeg7:MediaUri>http://i.ytimg.com/vi/wMc_5-RSWeg/mqdefault.jpg</mpeg7:MediaUri>
              </mpeg7:TitleImage>
            </tva:PromotionalMedia>
            <tva:PromotionalMedia>
              <mpeg7:TitleImage>
                <mpeg7:MediaUri>http://i.ytimg.com/vi/wMc_5-RSWeg/hqdefault.jpg</mpeg7:MediaUri>
              </mpeg7:TitleImage>
            </tva:PromotionalMedia>
            <tva:PromotionalMedia>
              <mpeg7:TitleImage>
                <mpeg7:MediaUri>http://i.ytimg.com/vi/wMc_5-RSWeg/1.jpg</mpeg7:MediaUri>
                <mpeg7:MediaTimePoint>T00:00:55:500F1000</mpeg7:MediaTimePoint>
              </mpeg7:TitleImage>
            </tva:PromotionalMedia>
            <tva:PromotionalMedia>
              <mpeg7:TitleImage>
                <mpeg7:MediaUri>http://i.ytimg.com/vi/wMc_5-RSWeg/2.jpg</mpeg7:MediaUri>
                <mpeg7:MediaTimePoint>T00:01:51</mpeg7:MediaTimePoint>
              </mpeg7:TitleImage>
            </tva:PromotionalMedia>
            <tva:PromotionalMedia>
              <mpeg7:TitleImage>
                <mpeg7:MediaUri>http://i.ytimg.com/vi/wMc_5-RSWeg/3.jpg</mpeg7:MediaUri>
                <mpeg7:MediaTimePoint>T00:02:46:500F1000</mpeg7:MediaTimePoint>
              </mpeg7:TitleImage>
            </tva:PromotionalMedia>
          </tva:RelatedMaterial>
          <tva:RelatedMaterial>
            <tva:HowRelated href="urn:tva:metadata:cs:HowRelatedCS:2007:6">
              <tva:Name xml:lang="en">Recommendation</tva:Name>
              <tva:Definition xml:lang="en">The reference points to a resource recommended the provider of the current resource. The service provider considers there to be similarities between the
			currently described resource and the referenced resource. Example: This could provide access to previous or next episodes or to all episodes (the parent series as a whole).
			Suggestion to record a programme which the broadcaster recommends because of what the user is watching.It could also point to a Web site proposing related programmes
			‘recommended’ by the service provider. A recommendation can be used to suggest content or services or services bundles with a similar subject.</tva:Definition>
            </tva:HowRelated>
            <tva:Format href="urn:tva:metadata:cs:FormatCS:2011:2.7.3.11">
              <tva:Name xml:lang="en">Non-linear audio-video</tva:Name>
              <tva:Definition xml:lang="en">Services where the interaction is based mostly around choosing alternate audio or video files - VOD and AOD, maybe combined with 2.1.1.15 (multi stream)</tva:Definition>
            </tva:Format>
            <tva:MediaLocator>
              <mpeg7:MediaUri>crid://youtube.com/9l2_SaqFfWY</mpeg7:MediaUri>
            </tva:MediaLocator>
            <tva:PromotionalText xml:lang="eng">Iss Pyaar Ko Kya Naam Doon - 4th september 2012 part 1 HD watch online</tva:PromotionalText>
            <tva:PromotionalMedia>
              <mpeg7:TitleImage>
                <mpeg7:MediaUri>http://i.ytimg.com/vi/9l2_SaqFfWY/default.jpg</mpeg7:MediaUri>
                <mpeg7:MediaTimePoint>T00:03:42</mpeg7:MediaTimePoint>
              </mpeg7:TitleImage>
            </tva:PromotionalMedia>
            <tva:PromotionalMedia>
              <mpeg7:TitleImage>
                <mpeg7:MediaUri>http://i.ytimg.com/vi/9l2_SaqFfWY/mqdefault.jpg</mpeg7:MediaUri>
              </mpeg7:TitleImage>
            </tva:PromotionalMedia>
            <tva:PromotionalMedia>
              <mpeg7:TitleImage>
                <mpeg7:MediaUri>http://i.ytimg.com/vi/9l2_SaqFfWY/hqdefault.jpg</mpeg7:MediaUri>
              </mpeg7:TitleImage>
            </tva:PromotionalMedia>
            <tva:PromotionalMedia>
              <mpeg7:TitleImage>
                <mpeg7:MediaUri>http://i.ytimg.com/vi/9l2_SaqFfWY/1.jpg</mpeg7:MediaUri>
                <mpeg7:MediaTimePoint>T00:01:51</mpeg7:MediaTimePoint>
              </mpeg7:TitleImage>
            </tva:PromotionalMedia>
            <tva:PromotionalMedia>
              <mpeg7:TitleImage>
                <mpeg7:MediaUri>http://i.ytimg.com/vi/9l2_SaqFfWY/2.jpg</mpeg7:MediaUri>
                <mpeg7:MediaTimePoint>T00:03:42</mpeg7:MediaTimePoint>
              </mpeg7:TitleImage>
            </tva:PromotionalMedia>
            <tva:PromotionalMedia>
              <mpeg7:TitleImage>
                <mpeg7:MediaUri>http://i.ytimg.com/vi/9l2_SaqFfWY/3.jpg</mpeg7:MediaUri>
                <mpeg7:MediaTimePoint>T00:05:33</mpeg7:MediaTimePoint>
              </mpeg7:TitleImage>
            </tva:PromotionalMedia>
          </tva:RelatedMaterial>
          <tva:RelatedMaterial>
            <tva:HowRelated href="urn:tva:metadata:cs:HowRelatedCS:2007:6">
              <tva:Name xml:lang="en">Recommendation</tva:Name>
              <tva:Definition xml:lang="en">The reference points to a resource recommended the provider of the current resource. The service provider considers there to be similarities between the
			currently described resource and the referenced resource. Example: This could provide access to previous or next episodes or to all episodes (the parent series as a whole).
			Suggestion to record a programme which the broadcaster recommends because of what the user is watching.It could also point to a Web site proposing related programmes
			‘recommended’ by the service provider. A recommendation can be used to suggest content or services or services bundles with a similar subject.</tva:Definition>
            </tva:HowRelated>
            <tva:Format href="urn:tva:metadata:cs:FormatCS:2011:2.7.3.11">
              <tva:Name xml:lang="en">Non-linear audio-video</tva:Name>
              <tva:Definition xml:lang="en">Services where the interaction is based mostly around choosing alternate audio or video files - VOD and AOD, maybe combined with 2.1.1.15 (multi stream)</tva:Definition>
            </tva:Format>
            <tva:MediaLocator>
              <mpeg7:MediaUri>crid://youtube.com/jVoISCHFFjs</mpeg7:MediaUri>
            </tva:MediaLocator>
            <tva:PromotionalText xml:lang="eng">Iss Pyaar Ko Kya Naam Doon - 4th september 2012 part 1 HD watch online</tva:PromotionalText>
            <tva:PromotionalMedia>
              <mpeg7:TitleImage>
                <mpeg7:MediaUri>http://i.ytimg.com/vi/jVoISCHFFjs/default.jpg</mpeg7:MediaUri>
                <mpeg7:MediaTimePoint>T00:03:14</mpeg7:MediaTimePoint>
              </mpeg7:TitleImage>
            </tva:PromotionalMedia>
            <tva:PromotionalMedia>
              <mpeg7:TitleImage>
                <mpeg7:MediaUri>http://i.ytimg.com/vi/jVoISCHFFjs/mqdefault.jpg</mpeg7:MediaUri>
              </mpeg7:TitleImage>
            </tva:PromotionalMedia>
            <tva:PromotionalMedia>
              <mpeg7:TitleImage>
                <mpeg7:MediaUri>http://i.ytimg.com/vi/jVoISCHFFjs/hqdefault.jpg</mpeg7:MediaUri>
              </mpeg7:TitleImage>
            </tva:PromotionalMedia>
            <tva:PromotionalMedia>
              <mpeg7:TitleImage>
                <mpeg7:MediaUri>http://i.ytimg.com/vi/jVoISCHFFjs/1.jpg</mpeg7:MediaUri>
                <mpeg7:MediaTimePoint>T00:01:37</mpeg7:MediaTimePoint>
              </mpeg7:TitleImage>
            </tva:PromotionalMedia>
            <tva:PromotionalMedia>
              <mpeg7:TitleImage>
                <mpeg7:MediaUri>http://i.ytimg.com/vi/jVoISCHFFjs/2.jpg</mpeg7:MediaUri>
                <mpeg7:MediaTimePoint>T00:03:14</mpeg7:MediaTimePoint>
              </mpeg7:TitleImage>
            </tva:PromotionalMedia>
            <tva:PromotionalMedia>
              <mpeg7:TitleImage>
                <mpeg7:MediaUri>http://i.ytimg.com/vi/jVoISCHFFjs/3.jpg</mpeg7:MediaUri>
                <mpeg7:MediaTimePoint>T00:04:51</mpeg7:MediaTimePoint>
              </mpeg7:TitleImage>
            </tva:PromotionalMedia>
          </tva:RelatedMaterial>
          <tva:RelatedMaterial>
            <tva:HowRelated href="urn:tva:metadata:cs:HowRelatedCS:2007:6">
              <tva:Name xml:lang="en">Recommendation</tva:Name>
              <tva:Definition xml:lang="en">The reference points to a resource recommended the provider of the current resource. The service provider considers there to be similarities between the
			currently described resource and the referenced resource. Example: This could provide access to previous or next episodes or to all episodes (the parent series as a whole).
			Suggestion to record a programme which the broadcaster recommends because of what the user is watching.It could also point to a Web site proposing related programmes
			‘recommended’ by the service provider. A recommendation can be used to suggest content or services or services bundles with a similar subject.</tva:Definition>
            </tva:HowRelated>
            <tva:Format href="urn:tva:metadata:cs:FormatCS:2011:2.7.3.11">
              <tva:Name xml:lang="en">Non-linear audio-video</tva:Name>
              <tva:Definition xml:lang="en">Services where the interaction is based mostly around choosing alternate audio or video files - VOD and AOD, maybe combined with 2.1.1.15 (multi stream)</tva:Definition>
            </tva:Format>
            <tva:MediaLocator>
              <mpeg7:MediaUri>crid://youtube.com/LJWqw5ALO30</mpeg7:MediaUri>
            </tva:MediaLocator>
            <tva:PromotionalText xml:lang="eng">Iss Pyaar Ko Kya Naam Doon -4th september 2012 part 1 HD</tva:PromotionalText>
            <tva:PromotionalMedia>
              <mpeg7:TitleImage>
                <mpeg7:MediaUri>http://i.ytimg.com/vi/LJWqw5ALO30/default.jpg</mpeg7:MediaUri>
                <mpeg7:MediaTimePoint>T00:02:39</mpeg7:MediaTimePoint>
              </mpeg7:TitleImage>
            </tva:PromotionalMedia>
            <tva:PromotionalMedia>
              <mpeg7:TitleImage>
                <mpeg7:MediaUri>http://i.ytimg.com/vi/LJWqw5ALO30/mqdefault.jpg</mpeg7:MediaUri>
              </mpeg7:TitleImage>
            </tva:PromotionalMedia>
            <tva:PromotionalMedia>
              <mpeg7:TitleImage>
                <mpeg7:MediaUri>http://i.ytimg.com/vi/LJWqw5ALO30/hqdefault.jpg</mpeg7:MediaUri>
              </mpeg7:TitleImage>
            </tva:PromotionalMedia>
            <tva:PromotionalMedia>
              <mpeg7:TitleImage>
                <mpeg7:MediaUri>http://i.ytimg.com/vi/LJWqw5ALO30/1.jpg</mpeg7:MediaUri>
                <mpeg7:MediaTimePoint>T00:01:19:500F1000</mpeg7:MediaTimePoint>
              </mpeg7:TitleImage>
            </tva:PromotionalMedia>
            <tva:PromotionalMedia>
              <mpeg7:TitleImage>
                <mpeg7:MediaUri>http://i.ytimg.com/vi/LJWqw5ALO30/2.jpg</mpeg7:MediaUri>
                <mpeg7:MediaTimePoint>T00:02:39</mpeg7:MediaTimePoint>
              </mpeg7:TitleImage>
            </tva:PromotionalMedia>
            <tva:PromotionalMedia>
              <mpeg7:TitleImage>
                <mpeg7:MediaUri>http://i.ytimg.com/vi/LJWqw5ALO30/3.jpg</mpeg7:MediaUri>
                <mpeg7:MediaTimePoint>T00:03:58:500F1000</mpeg7:MediaTimePoint>
              </mpeg7:TitleImage>
            </tva:PromotionalMedia>
          </tva:RelatedMaterial>
          <tva:RelatedMaterial>
            <tva:HowRelated href="urn:tva:metadata:cs:HowRelatedCS:2007:19">
              <tva:Name xml:lang="en">Promotional Still Image</tva:Name>
              <tva:Definition xml:lang="en">The resource points to a promotional still image for the content programme.</tva:Definition>
            </tva:HowRelated>
            <tva:MediaLocator>
              <mpeg7:MediaUri>http://i.ytimg.com/vi/i1_ZXeXcjT0/mqdefault.jpg</mpeg7:MediaUri>
            </tva:MediaLocator>
          </tva:RelatedMaterial>
          <tva:RelatedMaterial>
            <tva:HowRelated href="urn:tva:metadata:cs:HowRelatedCS:2007:19">
              <tva:Name xml:lang="en">Promotional Still Image</tva:Name>
              <tva:Definition xml:lang="en">The resource points to a promotional still image for the content programme.</tva:Definition>
            </tva:HowRelated>
            <tva:MediaLocator>
              <mpeg7:MediaUri>http://i.ytimg.com/vi/i1_ZXeXcjT0/3.jpg</mpeg7:MediaUri>
            </tva:MediaLocator>
          </tva:RelatedMaterial>
          <tva:RelatedMaterial>
            <tva:HowRelated href="urn:tva:metadata:cs:HowRelatedCS:2007:19">
              <tva:Name xml:lang="en">Promotional Still Image</tva:Name>
              <tva:Definition xml:lang="en">The resource points to a promotional still image for the content programme.</tva:Definition>
            </tva:HowRelated>
            <tva:MediaLocator>
              <mpeg7:MediaUri>http://i.ytimg.com/vi/i1_ZXeXcjT0/2.jpg</mpeg7:MediaUri>
            </tva:MediaLocator>
          </tva:RelatedMaterial>
          <tva:RelatedMaterial>
            <tva:HowRelated href="urn:tva:metadata:cs:HowRelatedCS:2007:19">
              <tva:Name xml:lang="en">Promotional Still Image</tva:Name>
              <tva:Definition xml:lang="en">The resource points to a promotional still image for the content programme.</tva:Definition>
            </tva:HowRelated>
            <tva:MediaLocator>
              <mpeg7:MediaUri>http://i.ytimg.com/vi/i1_ZXeXcjT0/hqdefault.jpg</mpeg7:MediaUri>
            </tva:MediaLocator>
          </tva:RelatedMaterial>
          <tva:RelatedMaterial>
            <tva:HowRelated href="urn:tva:metadata:cs:HowRelatedCS:2007:19">
              <tva:Name xml:lang="en">Promotional Still Image</tva:Name>
              <tva:Definition xml:lang="en">The resource points to a promotional still image for the content programme.</tva:Definition>
            </tva:HowRelated>
            <tva:MediaLocator>
              <mpeg7:MediaUri>http://i.ytimg.com/vi/i1_ZXeXcjT0/1.jpg</mpeg7:MediaUri>
            </tva:MediaLocator>
          </tva:RelatedMaterial>
          <tva:RelatedMaterial>
            <tva:HowRelated href="urn:tva:metadata:cs:HowRelatedCS:2007:19">
              <tva:Name xml:lang="en">Promotional Still Image</tva:Name>
              <tva:Definition xml:lang="en">The resource points to a promotional still image for the content programme.</tva:Definition>
            </tva:HowRelated>
            <tva:MediaLocator>
              <mpeg7:MediaUri>http://i.ytimg.com/vi/i1_ZXeXcjT0/default.jpg</mpeg7:MediaUri>
            </tva:MediaLocator>
          </tva:RelatedMaterial>
        </tva:BasicDescription>
        <tva:AVAttributes>
          <tva:AudioAttributes/>
          <tva:VideoAttributes>
            <tva:Color type="color"/>
          </tva:VideoAttributes>
        </tva:AVAttributes>
      </tva:ProgramInformation>
    </tva:ProgramInformationTable>
    <tva:ProgramLocationTable>
      <tva:OnDemandService fragmentId="73" fragmentVersion="0" serviceIDRef="YouTube">
        <tva:OnDemandProgram fragmentId="74" fragmentVersion="0" serviceIDRef="YouTube">
          <tva:Program crid="crid://youtube.com/i1_ZXeXcjT0"/>
          <tva:ProgramURL>http://www.youtube.com/v/i1_ZXeXcjT0?version=3&amp;f=videos&amp;c=iNEM4U&amp;app=youtube_gdata</tva:ProgramURL>
          <tva:InstanceDescription>
            <tva:AVAttributes>
              <tva:AudioAttributes/>
              <tva:VideoAttributes>
                <tva:Color type="color"/>
              </tva:VideoAttributes>
            </tva:AVAttributes>
          </tva:InstanceDescription>
          <tva:PublishedDuration>PT1.239S</tva:PublishedDuration>
        </tva:OnDemandProgram>
        <tva:OnDemandProgram fragmentId="75" fragmentVersion="0" serviceIDRef="YouTube">
          <tva:Program crid="crid://youtube.com/i1_ZXeXcjT0"/>
          <tva:ProgramURL>rtsp://v2.cache8.c.youtube.com/CioLENy73wIaIQk9jdzlXdlfixMYDSANFEIGaU5FTTRVSAZSBnZpZGVvcww=/0/0/0/video.3gp</tva:ProgramURL>
          <tva:InstanceDescription>
            <tva:AVAttributes>
              <tva:AudioAttributes/>
              <tva:VideoAttributes>
                <tva:Color type="color"/>
              </tva:VideoAttributes>
            </tva:AVAttributes>
          </tva:InstanceDescription>
          <tva:PublishedDuration>PT1.239S</tva:PublishedDuration>
        </tva:OnDemandProgram>
        <tva:OnDemandProgram fragmentId="76" fragmentVersion="0" serviceIDRef="YouTube">
          <tva:Program crid="crid://youtube.com/i1_ZXeXcjT0"/>
          <tva:ProgramURL>rtsp://v1.cache8.c.youtube.com/CioLENy73wIaIQk9jdzlXdlfixMYESARFEIGaU5FTTRVSAZSBnZpZGVvcww=/0/0/0/video.3gp</tva:ProgramURL>
          <tva:InstanceDescription>
            <tva:AVAttributes>
              <tva:AudioAttributes/>
              <tva:VideoAttributes>
                <tva:Color type="color"/>
              </tva:VideoAttributes>
            </tva:AVAttributes>
          </tva:InstanceDescription>
          <tva:PublishedDuration>PT1.239S</tva:PublishedDuration>
        </tva:OnDemandProgram>
      </tva:OnDemandService>
    </tva:ProgramLocationTable>
    <tva:ServiceInformationTable>
      <tva:ServiceInformation fragmentId="95" fragmentVersion="0" serviceId="YouTube">
        <tva:Name>YouTube</tva:Name>
        <tva:ServiceURL>http://www.youtube.com/</tva:ServiceURL>
        <tva:Logo>
          <mpeg7:MediaUri>file:/I:/IRT/F-RFK/workspace/YouTube%20CIS/java_classes/de/irt/inem4u/youtube/YouTubeContentInformationSource.png</mpeg7:MediaUri>
        </tva:Logo>
      </tva:ServiceInformation>
    </tva:ServiceInformationTable>
    <tva:ProgramReviewTable>
      <tva:Review fragmentId="77" fragmentVersion="0" programId="crid://youtube.com/i1_ZXeXcjT0">
        <Adult>false</Adult>
        <Spam>false</Spam>
        <tva:FreeTextReview xml:lang="en">i totally agree with u, but  i can't get why anjali keep trusting shyam !!we know  she love him to death,but what about her chotti did she﻿ think about him suffring for her and putting himself on fire to make her safe and happy ?she is too weak ,she must learn some lessons from khushi :))</tva:FreeTextReview>
        <tva:Reviewer>
          <tva:PersonName>
            <mpeg7:FamilyName>ayaakbar</mpeg7:FamilyName>
          </tva:PersonName>
        </tva:Reviewer>
        <tva:Reviewer>
          <tva:Publication>2012-09-05T09:42:02+02:00</tva:Publication>
        </tva:Reviewer>
        <tva:ReviewReference>http://gdata.youtube.com/feeds/api/users/ayaakbar</tva:ReviewReference>
      </tva:Review>
      <tva:Review fragmentId="78" fragmentVersion="0" programId="crid://youtube.com/i1_ZXeXcjT0">
        <Adult>false</Adult>
        <Spam>false</Spam>
        <tva:FreeTextReview xml:lang="en">i love the way of arnav beatng 2 shym keep it up arnav....beat him more as u can....i hate dadi﻿ role....I yhink she is wth shyam</tva:FreeTextReview>
        <tva:Reviewer>
          <tva:PersonName>
            <mpeg7:FamilyName>anna12328007505</mpeg7:FamilyName>
          </tva:PersonName>
        </tva:Reviewer>
        <tva:Reviewer>
          <tva:Publication>2012-09-05T06:44:41+02:00</tva:Publication>
        </tva:Reviewer>
        <tva:ReviewReference>http://gdata.youtube.com/feeds/api/users/anna12328007505</tva:ReviewReference>
      </tva:Review>
      <tva:Review fragmentId="79" fragmentVersion="0" programId="crid://youtube.com/i1_ZXeXcjT0">
        <Adult>false</Adult>
        <Spam>false</Spam>
        <tva:FreeTextReview xml:lang="en">Shyam good actor n very﻿ good villian n dadi omg hate her</tva:FreeTextReview>
        <tva:Reviewer>
          <tva:PersonName>
            <mpeg7:FamilyName>115asu</mpeg7:FamilyName>
          </tva:PersonName>
        </tva:Reviewer>
        <tva:Reviewer>
          <tva:Publication>2012-09-05T09:26:34+02:00</tva:Publication>
        </tva:Reviewer>
        <tva:ReviewReference>http://gdata.youtube.com/feeds/api/users/115asu</tva:ReviewReference>
      </tva:Review>
      <tva:Review fragmentId="80" fragmentVersion="0" programId="crid://youtube.com/i1_ZXeXcjT0">
        <Adult>false</Adult>
        <Spam>false</Spam>
        <tva:FreeTextReview xml:lang="en">Serial has become weird.One minute Arnav tells everyone,not invite Shyam inthe house,next min.shyam is﻿ inside the house.What happened to security.I hate Anjali's expressions,she seems to be unaware of her surroundings.And about Shyam's acting skills.it is MONOTONUS.twisted grins and monster faces.The serial is fizzing out,even arshi romance has become repetative.Best way is to stop watching.And if the track continues,many will join me.</tva:FreeTextReview>
        <tva:Reviewer>
          <tva:PersonName>
            <mpeg7:FamilyName>daffodil1972</mpeg7:FamilyName>
          </tva:PersonName>
        </tva:Reviewer>
        <tva:Reviewer>
          <tva:Publication>2012-09-05T08:28:12+02:00</tva:Publication>
        </tva:Reviewer>
        <tva:ReviewReference>http://gdata.youtube.com/feeds/api/users/daffodil1972</tva:ReviewReference>
      </tva:Review>
      <tva:Review fragmentId="81" fragmentVersion="0" programId="crid://youtube.com/i1_ZXeXcjT0">
        <Adult>false</Adult>
        <Spam>false</Spam>
        <tva:FreeTextReview xml:lang="en">I remember Anjalis room was full of glass particals and her blood due to bleeding of her feet.........what happen to that no one clean that room....Please CVs make﻿ sure u clear this things up before moving story ahead....Make sure u do give credit to ur viewers intelligence..</tva:FreeTextReview>
        <tva:Reviewer>
          <tva:PersonName>
            <mpeg7:FamilyName>lotro0275</mpeg7:FamilyName>
          </tva:PersonName>
        </tva:Reviewer>
        <tva:Reviewer>
          <tva:Publication>2012-09-05T07:46:12+02:00</tva:Publication>
        </tva:Reviewer>
        <tva:ReviewReference>http://gdata.youtube.com/feeds/api/users/lotro0275</tva:ReviewReference>
      </tva:Review>
      <tva:Review fragmentId="82" fragmentVersion="0" programId="crid://youtube.com/i1_ZXeXcjT0">
        <Adult>false</Adult>
        <Spam>false</Spam>
        <tva:FreeTextReview xml:lang="en">Arnav should join the wrestling...
And whts wrong with dadi?? she jus came yesterday and acts like she was with arnav and anjali for the past 10 years!!! And shyam? mind if you do the Arshi fans a help?? Can﻿ YOU KILL DADI INSTEAD OD ANJALI??? It will earn you some respect, i guess..</tva:FreeTextReview>
        <tva:Reviewer>
          <tva:PersonName>
            <mpeg7:FamilyName>aruvani97</mpeg7:FamilyName>
          </tva:PersonName>
        </tva:Reviewer>
        <tva:Reviewer>
          <tva:Publication>2012-09-05T06:43:39+02:00</tva:Publication>
        </tva:Reviewer>
        <tva:ReviewReference>http://gdata.youtube.com/feeds/api/users/aruvani97</tva:ReviewReference>
      </tva:Review>
      <tva:Review fragmentId="83" fragmentVersion="0" programId="crid://youtube.com/i1_ZXeXcjT0">
        <Adult>false</Adult>
        <Spam>false</Spam>
        <tva:FreeTextReview xml:lang="en">shyaam is good﻿ actor</tva:FreeTextReview>
        <tva:Reviewer>
          <tva:PersonName>
            <mpeg7:GivenName>Noor</mpeg7:GivenName>
            <mpeg7:FamilyName>Chumber</mpeg7:FamilyName>
          </tva:PersonName>
        </tva:Reviewer>
        <tva:Reviewer>
          <tva:Publication>2012-09-05T07:02:15+02:00</tva:Publication>
        </tva:Reviewer>
        <tva:ReviewReference>http://gdata.youtube.com/feeds/api/users/g10OdeVvcjJJ2RMbqievSw</tva:ReviewReference>
      </tva:Review>
      <tva:Review fragmentId="84" fragmentVersion="0" programId="crid://youtube.com/i1_ZXeXcjT0">
        <Adult>false</Adult>
        <Spam>false</Spam>
        <tva:FreeTextReview xml:lang="en">Shyam Bagairat kia﻿ acting karta﻿ hai!!!</tva:FreeTextReview>
        <tva:Reviewer>
          <tva:PersonName>
            <mpeg7:FamilyName>daniyalfabre</mpeg7:FamilyName>
          </tva:PersonName>
        </tva:Reviewer>
        <tva:Reviewer>
          <tva:Publication>2012-09-05T09:56:17+02:00</tva:Publication>
        </tva:Reviewer>
        <tva:ReviewReference>http://gdata.youtube.com/feeds/api/users/daniyalfabre</tva:ReviewReference>
      </tva:Review>
      <tva:Review fragmentId="85" fragmentVersion="0" programId="crid://youtube.com/i1_ZXeXcjT0">
        <Adult>true</Adult>
        <Spam>false</Spam>
        <tva:FreeTextReview xml:lang="en">5:50 the sexiest face i have Shaym eva make !
ughhh! how ugli﻿ can he get! :/
&amp; he deserves to DIE!
everyone ride a car over him! arghh -.- typical kunt!</tva:FreeTextReview>
        <tva:Reviewer>
          <tva:PersonName>
            <mpeg7:FamilyName>ShahnazzAli143</mpeg7:FamilyName>
          </tva:PersonName>
        </tva:Reviewer>
        <tva:Reviewer>
          <tva:Publication>2012-09-05T09:04:21+02:00</tva:Publication>
        </tva:Reviewer>
        <tva:ReviewReference>http://gdata.youtube.com/feeds/api/users/ShahnazzAli143</tva:ReviewReference>
      </tva:Review>
      <tva:Review fragmentId="86" fragmentVersion="0" programId="crid://youtube.com/i1_ZXeXcjT0">
        <Adult>false</Adult>
        <Spam>false</Spam>
        <tva:FreeTextReview xml:lang="en">but i﻿ feel its not enough u see, 'coz this snakwa deserves more 
he should be beaten to the where he can't even see his filthy face (not Abaas) in the mirror.</tva:FreeTextReview>
        <tva:Reviewer>
          <tva:PersonName>
            <mpeg7:FamilyName>yuvake</mpeg7:FamilyName>
          </tva:PersonName>
        </tva:Reviewer>
        <tva:Reviewer>
          <tva:Publication>2012-09-05T10:28:33+02:00</tva:Publication>
        </tva:Reviewer>
        <tva:ReviewReference>http://gdata.youtube.com/feeds/api/users/yuvake</tva:ReviewReference>
      </tva:Review>
      <tva:Review fragmentId="87" fragmentVersion="0" programId="crid://youtube.com/i1_ZXeXcjT0">
        <Adult>false</Adult>
        <Spam>false</Spam>
        <tva:FreeTextReview xml:lang="en">shyaam is really a nice actor even﻿ he is playing a negative role .......love him</tva:FreeTextReview>
        <tva:Reviewer>
          <tva:PersonName>
            <mpeg7:FamilyName>munjaraf1</mpeg7:FamilyName>
          </tva:PersonName>
        </tva:Reviewer>
        <tva:Reviewer>
          <tva:Publication>2012-09-05T06:18:44+02:00</tva:Publication>
        </tva:Reviewer>
        <tva:ReviewReference>http://gdata.youtube.com/feeds/api/users/munjaraf1</tva:ReviewReference>
      </tva:Review>
      <tva:Review fragmentId="88" fragmentVersion="0" programId="crid://youtube.com/i1_ZXeXcjT0">
        <Adult>false</Adult>
        <Spam>false</Spam>
        <tva:FreeTextReview xml:lang="en">How much betrayed and shattered Arnav will feel when he will get to know about anjali meeting shyam and whatever has to come from Garimas side..
 He trusts Anjali so much :(﻿</tva:FreeTextReview>
        <tva:Reviewer>
          <tva:PersonName>
            <mpeg7:GivenName>Sia</mpeg7:GivenName>
            <mpeg7:FamilyName>Khan</mpeg7:FamilyName>
          </tva:PersonName>
        </tva:Reviewer>
        <tva:Reviewer>
          <tva:Publication>2012-09-05T08:05:34+02:00</tva:Publication>
        </tva:Reviewer>
        <tva:ReviewReference>http://gdata.youtube.com/feeds/api/users/CHsT-R4RyDu0wrgbtobkrw</tva:ReviewReference>
      </tva:Review>
      <tva:Review fragmentId="89" fragmentVersion="0" programId="crid://youtube.com/i1_ZXeXcjT0">
        <Adult>false</Adult>
        <Spam>false</Spam>
        <tva:FreeTextReview xml:lang="en">whatever shyam﻿ did in past with Arnav and Khushi, it didnt bother me much. part of play !!! .But killing one's own child.. this is simply TOO MUCH.. writers! not a very nice thing to show!!!</tva:FreeTextReview>
        <tva:Reviewer>
          <tva:PersonName>
            <mpeg7:FamilyName>MsSyednaqvi</mpeg7:FamilyName>
          </tva:PersonName>
        </tva:Reviewer>
        <tva:Reviewer>
          <tva:Publication>2012-09-05T10:08:32+02:00</tva:Publication>
        </tva:Reviewer>
        <tva:ReviewReference>http://gdata.youtube.com/feeds/api/users/MsSyednaqvi</tva:ReviewReference>
      </tva:Review>
      <tva:Review fragmentId="90" fragmentVersion="0" programId="crid://youtube.com/i1_ZXeXcjT0">
        <Adult>false</Adult>
        <Spam>false</Spam>
        <tva:FreeTextReview xml:lang="en">Urgh I hate Anjali, her own stupid husband killed her baby and she still worships﻿ him</tva:FreeTextReview>
        <tva:Reviewer>
          <tva:PersonName>
            <mpeg7:FamilyName>im4urumine1</mpeg7:FamilyName>
          </tva:PersonName>
        </tva:Reviewer>
        <tva:Reviewer>
          <tva:Publication>2012-09-05T06:29:22+02:00</tva:Publication>
        </tva:Reviewer>
        <tva:ReviewReference>http://gdata.youtube.com/feeds/api/users/im4urumine1</tva:ReviewReference>
      </tva:Review>
      <tva:Review fragmentId="91" fragmentVersion="0" programId="crid://youtube.com/i1_ZXeXcjT0">
        <Adult>false</Adult>
        <Spam>false</Spam>
        <tva:FreeTextReview xml:lang="en">Shyam is so cruel
this﻿ shouldnt happen with anjali :(</tva:FreeTextReview>
        <tva:Reviewer>
          <tva:PersonName>
            <mpeg7:GivenName>Sia</mpeg7:GivenName>
            <mpeg7:FamilyName>Khan</mpeg7:FamilyName>
          </tva:PersonName>
        </tva:Reviewer>
        <tva:Reviewer>
          <tva:Publication>2012-09-05T07:35:59+02:00</tva:Publication>
        </tva:Reviewer>
        <tva:ReviewReference>http://gdata.youtube.com/feeds/api/users/CHsT-R4RyDu0wrgbtobkrw</tva:ReviewReference>
      </tva:Review>
      <tva:Review fragmentId="92" fragmentVersion="0" programId="crid://youtube.com/i1_ZXeXcjT0">
        <Adult>false</Adult>
        <Spam>false</Spam>
        <tva:FreeTextReview xml:lang="en">shyam is such a good actor, he's a great﻿ villain!</tva:FreeTextReview>
        <tva:Reviewer>
          <tva:PersonName>
            <mpeg7:FamilyName>justtcallmedeath</mpeg7:FamilyName>
          </tva:PersonName>
        </tva:Reviewer>
        <tva:Reviewer>
          <tva:Publication>2012-09-05T07:17:10+02:00</tva:Publication>
        </tva:Reviewer>
        <tva:ReviewReference>http://gdata.youtube.com/feeds/api/users/justtcallmedeath</tva:ReviewReference>
      </tva:Review>
      <tva:Review fragmentId="93" fragmentVersion="0" programId="crid://youtube.com/i1_ZXeXcjT0">
        <Adult>true</Adult>
        <Spam>false</Spam>
        <tva:FreeTextReview xml:lang="en">Thank god for the punches. Now everytime I rewatch an episode or Shyam pisses me off, I'm going to come back and replay the slap and punch(ES) scene a bazillion times﻿ to feel better. Well played, ASR.</tva:FreeTextReview>
        <tva:Reviewer>
          <tva:PersonName>
            <mpeg7:FamilyName>bucky232</mpeg7:FamilyName>
          </tva:PersonName>
        </tva:Reviewer>
        <tva:Reviewer>
          <tva:Publication>2012-09-05T06:24:13+02:00</tva:Publication>
        </tva:Reviewer>
        <tva:ReviewReference>http://gdata.youtube.com/feeds/api/users/bucky232</tva:ReviewReference>
      </tva:Review>
      <tva:Review fragmentId="94" fragmentVersion="0" programId="crid://youtube.com/i1_ZXeXcjT0">
        <Adult>false</Adult>
        <Spam>false</Spam>
        <tva:FreeTextReview xml:lang="en">Mam, please get them marry soon and together. then  create any problem we﻿ will tolerate.  plz. don't break their marriage becaz they have already married</tva:FreeTextReview>
        <tva:Reviewer>
          <tva:PersonName>
            <mpeg7:GivenName>sabita</mpeg7:GivenName>
            <mpeg7:FamilyName>sahoo</mpeg7:FamilyName>
          </tva:PersonName>
        </tva:Reviewer>
        <tva:Reviewer>
          <tva:Publication>2012-09-05T07:44:54+02:00</tva:Publication>
        </tva:Reviewer>
        <tva:ReviewReference>http://gdata.youtube.com/feeds/api/users/pj2CbNl7HehOhXxW4rxWcA</tva:ReviewReference>
      </tva:Review>
      <ReviewerData>
        <Reviewer>
          <Username>ayaakbar</Username>
          <Age>28</Age>
          <FriendsAdded>0</FriendsAdded>
          <Gender>FEMALE</Gender>
          <LastWebAccess>2012-08-21 19:42</LastWebAccess>
          <Location>FR</Location>
          <SubscriberCount>0</SubscriberCount>
          <UserSubscriptionsAdded>0</UserSubscriptionsAdded>
          <VideosCommented>24</VideosCommented>
          <VideosFavourited>0</VideosFavourited>
          <VideosRated>0</VideosRated>
          <VideosShared>0</VideosShared>
          <VideosUploaded>0</VideosUploaded>
          <UserAccountClosed>false</UserAccountClosed>
          <UserAccountSuspended>false</UserAccountSuspended>
        </Reviewer>
        <Reviewer>
          <Username>anna12328007505</Username>
          <FriendsAdded>0</FriendsAdded>
          <Gender>FEMALE</Gender>
          <LastWebAccess>2011-09-07 13:38</LastWebAccess>
          <Location>PK</Location>
          <SubscriberCount>0</SubscriberCount>
          <UserSubscriptionsAdded>3</UserSubscriptionsAdded>
          <VideosCommented>11</VideosCommented>
          <VideosFavourited>0</VideosFavourited>
          <VideosRated>11</VideosRated>
          <VideosShared>0</VideosShared>
          <VideosUploaded>0</VideosUploaded>
          <UserAccountClosed>false</UserAccountClosed>
          <UserAccountSuspended>false</UserAccountSuspended>
        </Reviewer>
        <Reviewer>
          <Username>115asu</Username>
          <Age>36</Age>
          <FriendsAdded>0</FriendsAdded>
          <Gender>FEMALE</Gender>
          <LastWebAccess>2012-09-05 07:26</LastWebAccess>
          <Location>GB</Location>
          <SubscriberCount>0</SubscriberCount>
          <UserSubscriptionsAdded>0</UserSubscriptionsAdded>
          <VideosCommented>6</VideosCommented>
          <VideosFavourited>14</VideosFavourited>
          <VideosRated>5</VideosRated>
          <VideosShared>0</VideosShared>
          <VideosUploaded>0</VideosUploaded>
          <UserAccountClosed>false</UserAccountClosed>
          <UserAccountSuspended>false</UserAccountSuspended>
        </Reviewer>
        <Reviewer>
          <Username>daffodil1972</Username>
          <Age>40</Age>
          <FriendsAdded>0</FriendsAdded>
          <Gender>FEMALE</Gender>
          <LastWebAccess>2011-06-20 10:15</LastWebAccess>
          <Location>IN</Location>
          <SubscriberCount>0</SubscriberCount>
          <UserSubscriptionsAdded>0</UserSubscriptionsAdded>
          <VideosCommented>9</VideosCommented>
          <VideosFavourited>0</VideosFavourited>
          <VideosRated>1</VideosRated>
          <VideosShared>0</VideosShared>
          <VideosUploaded>1</VideosUploaded>
          <UserAccountClosed>false</UserAccountClosed>
          <UserAccountSuspended>false</UserAccountSuspended>
        </Reviewer>
        <Reviewer>
          <Username>lotro0275</Username>
          <Age>37</Age>
          <FriendsAdded>0</FriendsAdded>
          <Gender>FEMALE</Gender>
          <LastWebAccess>2012-06-05 06:39</LastWebAccess>
          <Location>IN</Location>
          <SubscriberCount>1</SubscriberCount>
          <UserSubscriptionsAdded>0</UserSubscriptionsAdded>
          <VideosCommented>2</VideosCommented>
          <VideosFavourited>0</VideosFavourited>
          <VideosRated>23</VideosRated>
          <VideosShared>0</VideosShared>
          <VideosUploaded>0</VideosUploaded>
          <UserAccountClosed>false</UserAccountClosed>
          <UserAccountSuspended>false</UserAccountSuspended>
        </Reviewer>
        <Reviewer>
          <Username>aruvani97</Username>
          <Age>21</Age>
          <Books>No tImE</Books>
          <FriendsAdded>0</FriendsAdded>
          <Gender>FEMALE</Gender>
          <LastWebAccess>2012-05-18 04:58</LastWebAccess>
          <Location>SG</Location>
          <Music>bOlLyWoOd</Music>
          <SubscriberCount>126</SubscriberCount>
          <UserSubscriptionsAdded>9</UserSubscriptionsAdded>
          <VideosCommented>9</VideosCommented>
          <VideosFavourited>0</VideosFavourited>
          <VideosRated>6</VideosRated>
          <VideosShared>0</VideosShared>
          <VideosUploaded>1</VideosUploaded>
          <UserAccountClosed>false</UserAccountClosed>
          <UserAccountSuspended>false</UserAccountSuspended>
        </Reviewer>
        <Reviewer>
          <Username>Chumber</Username>
          <FriendsAdded>0</FriendsAdded>
          <SubscriberCount>0</SubscriberCount>
          <UserSubscriptionsAdded>0</UserSubscriptionsAdded>
          <VideosCommented>0</VideosCommented>
          <VideosFavourited>0</VideosFavourited>
          <VideosRated>0</VideosRated>
          <VideosShared>0</VideosShared>
          <VideosUploaded>0</VideosUploaded>
          <UserAccountClosed>true</UserAccountClosed>
          <UserAccountSuspended>false</UserAccountSuspended>
        </Reviewer>
        <Reviewer>
          <Username>daniyalfabre</Username>
          <Age>26</Age>
          <FriendsAdded>0</FriendsAdded>
          <Gender>MALE</Gender>
          <Hometown>Islamabad</Hometown>
          <Job>Student</Job>
          <LastWebAccess>2011-05-30 07:41</LastWebAccess>
          <Location>Islamabad, PK</Location>
          <Relationship>SINGLE</Relationship>
          <SubscriberCount>0</SubscriberCount>
          <UserSubscriptionsAdded>10</UserSubscriptionsAdded>
          <VideosCommented>11</VideosCommented>
          <VideosFavourited>1</VideosFavourited>
          <VideosRated>3</VideosRated>
          <VideosShared>0</VideosShared>
          <VideosUploaded>0</VideosUploaded>
          <UserAccountClosed>false</UserAccountClosed>
          <UserAccountSuspended>false</UserAccountSuspended>
        </Reviewer>
        <Reviewer>
          <Username>shahnazzali143</Username>
          <FriendsAdded>0</FriendsAdded>
          <Gender>FEMALE</Gender>
          <LastWebAccess>2012-06-17 08:03</LastWebAccess>
          <Location>AU</Location>
          <SubscriberCount>1</SubscriberCount>
          <UserSubscriptionsAdded>0</UserSubscriptionsAdded>
          <VideosCommented>8</VideosCommented>
          <VideosFavourited>0</VideosFavourited>
          <VideosRated>17</VideosRated>
          <VideosShared>0</VideosShared>
          <VideosUploaded>0</VideosUploaded>
          <UserAccountClosed>false</UserAccountClosed>
          <UserAccountSuspended>false</UserAccountSuspended>
        </Reviewer>
        <Reviewer>
          <Username>yuvake</Username>
          <Age>21</Age>
          <FriendsAdded>0</FriendsAdded>
          <Gender>FEMALE</Gender>
          <LastWebAccess>2012-09-01 08:09</LastWebAccess>
          <Location>IN</Location>
          <SubscriberCount>0</SubscriberCount>
          <UserSubscriptionsAdded>4</UserSubscriptionsAdded>
          <VideosCommented>5</VideosCommented>
          <VideosFavourited>0</VideosFavourited>
          <VideosRated>16</VideosRated>
          <VideosShared>0</VideosShared>
          <VideosUploaded>0</VideosUploaded>
          <UserAccountClosed>false</UserAccountClosed>
          <UserAccountSuspended>false</UserAccountSuspended>
        </Reviewer>
        <Reviewer>
          <Username>munjaraf1</Username>
          <Age>25</Age>
          <FriendsAdded>0</FriendsAdded>
          <Gender>MALE</Gender>
          <LastWebAccess>2011-12-17 10:26</LastWebAccess>
          <Location>AE</Location>
          <SubscriberCount>0</SubscriberCount>
          <UserSubscriptionsAdded>9</UserSubscriptionsAdded>
          <VideosCommented>9</VideosCommented>
          <VideosFavourited>0</VideosFavourited>
          <VideosRated>7</VideosRated>
          <VideosShared>0</VideosShared>
          <VideosUploaded>0</VideosUploaded>
          <UserAccountClosed>false</UserAccountClosed>
          <UserAccountSuspended>false</UserAccountSuspended>
        </Reviewer>
        <Reviewer>
          <Username>khan</Username>
          <Age>28</Age>
          <FriendsAdded>0</FriendsAdded>
          <LastWebAccess>2011-09-16 23:05</LastWebAccess>
          <Location>IE</Location>
          <SubscriberCount>71</SubscriberCount>
          <UserSubscriptionsAdded>0</UserSubscriptionsAdded>
          <VideosCommented>1</VideosCommented>
          <VideosFavourited>1</VideosFavourited>
          <VideosRated>1</VideosRated>
          <VideosShared>0</VideosShared>
          <VideosUploaded>0</VideosUploaded>
          <UserAccountClosed>false</UserAccountClosed>
          <UserAccountSuspended>false</UserAccountSuspended>
        </Reviewer>
        <Reviewer>
          <Username>mssyednaqvi</Username>
          <Age>33</Age>
          <FriendsAdded>0</FriendsAdded>
          <Gender>MALE</Gender>
          <LastWebAccess>2011-07-06 06:27</LastWebAccess>
          <Location>PK</Location>
          <SubscriberCount>0</SubscriberCount>
          <UserSubscriptionsAdded>1</UserSubscriptionsAdded>
          <VideosCommented>1</VideosCommented>
          <VideosFavourited>0</VideosFavourited>
          <VideosRated>0</VideosRated>
          <VideosShared>0</VideosShared>
          <VideosUploaded>0</VideosUploaded>
          <UserAccountClosed>false</UserAccountClosed>
          <UserAccountSuspended>false</UserAccountSuspended>
        </Reviewer>
        <Reviewer>
          <Username>im4urumine1</Username>
          <Age>28</Age>
          <FriendsAdded>0</FriendsAdded>
          <Gender>FEMALE</Gender>
          <LastWebAccess>2011-12-28 01:44</LastWebAccess>
          <Location>US</Location>
          <SubscriberCount>0</SubscriberCount>
          <UserSubscriptionsAdded>0</UserSubscriptionsAdded>
          <VideosCommented>20</VideosCommented>
          <VideosFavourited>0</VideosFavourited>
          <VideosRated>0</VideosRated>
          <VideosShared>0</VideosShared>
          <VideosUploaded>0</VideosUploaded>
          <UserAccountClosed>false</UserAccountClosed>
          <UserAccountSuspended>false</UserAccountSuspended>
        </Reviewer>
        <Reviewer>
          <Username>khan</Username>
          <Age>28</Age>
          <FriendsAdded>0</FriendsAdded>
          <LastWebAccess>2011-09-16 23:05</LastWebAccess>
          <Location>IE</Location>
          <SubscriberCount>71</SubscriberCount>
          <UserSubscriptionsAdded>0</UserSubscriptionsAdded>
          <VideosCommented>1</VideosCommented>
          <VideosFavourited>1</VideosFavourited>
          <VideosRated>1</VideosRated>
          <VideosShared>0</VideosShared>
          <VideosUploaded>0</VideosUploaded>
          <UserAccountClosed>false</UserAccountClosed>
          <UserAccountSuspended>false</UserAccountSuspended>
        </Reviewer>
        <Reviewer>
          <Username>justtcallmedeath</Username>
          <Age>19</Age>
          <FriendsAdded>0</FriendsAdded>
          <Gender>FEMALE</Gender>
          <LastWebAccess>2012-09-05 05:45</LastWebAccess>
          <Location>CA</Location>
          <SubscriberCount>2</SubscriberCount>
          <UserSubscriptionsAdded>4</UserSubscriptionsAdded>
          <VideosCommented>0</VideosCommented>
          <VideosFavourited>1</VideosFavourited>
          <VideosRated>20</VideosRated>
          <VideosShared>0</VideosShared>
          <VideosUploaded>0</VideosUploaded>
          <UserAccountClosed>false</UserAccountClosed>
          <UserAccountSuspended>false</UserAccountSuspended>
        </Reviewer>
        <Reviewer>
          <Username>bucky232</Username>
          <Age>25</Age>
          <FriendsAdded>0</FriendsAdded>
          <Gender>FEMALE</Gender>
          <LastWebAccess>2012-04-14 18:50</LastWebAccess>
          <Location>US</Location>
          <SubscriberCount>1</SubscriberCount>
          <UserSubscriptionsAdded>0</UserSubscriptionsAdded>
          <VideosCommented>16</VideosCommented>
          <VideosFavourited>0</VideosFavourited>
          <VideosRated>9</VideosRated>
          <VideosShared>0</VideosShared>
          <VideosUploaded>0</VideosUploaded>
          <UserAccountClosed>false</UserAccountClosed>
          <UserAccountSuspended>false</UserAccountSuspended>
        </Reviewer>
        <Reviewer>
          <Username>sahoo</Username>
          <Age>25</Age>
          <FriendsAdded>0</FriendsAdded>
          <Gender>FEMALE</Gender>
          <LastWebAccess>2011-12-05 16:08</LastWebAccess>
          <Location>US</Location>
          <SubscriberCount>0</SubscriberCount>
          <UserSubscriptionsAdded>0</UserSubscriptionsAdded>
          <VideosCommented>0</VideosCommented>
          <VideosFavourited>0</VideosFavourited>
          <VideosRated>0</VideosRated>
          <VideosShared>0</VideosShared>
          <VideosUploaded>0</VideosUploaded>
          <UserAccountClosed>false</UserAccountClosed>
          <UserAccountSuspended>false</UserAccountSuspended>
        </Reviewer>
      </ReviewerData>
    </tva:ProgramReviewTable>
  </tva:ProgramDescription>
</tva:TVAMain>